cdk_skill_management/__init__.py
cdk_skill_management/py.typed
cdk_skill_management/_jsii/__init__.py
cdk_skill_management/_jsii/cdk-skill-management@1.0.40.jsii.tgz
cdk_skill_management-1.0.40.dist-info/LICENSE
cdk_skill_management-1.0.40.dist-info/METADATA
cdk_skill_management-1.0.40.dist-info/WHEEL
cdk_skill_management-1.0.40.dist-info/top_level.txt
cdk_skill_management-1.0.40.dist-info/RECORD
