Metadata-Version: 2.1
Name: cdk-skill-management
Version: 1.0.40
Summary: CDK constructs to manage Alexa Skills
Home-page: https://github.com/t0bst4r/cdk-skill-management.git
Author: t0bst4r<82281152+t0bst4r@users.noreply.github.com>
License: MIT
Project-URL: Source, https://github.com/t0bst4r/cdk-skill-management.git
Classifier: Intended Audience :: Developers
Classifier: Operating System :: OS Independent
Classifier: Programming Language :: JavaScript
Classifier: Programming Language :: Python :: 3 :: Only
Classifier: Programming Language :: Python :: 3.8
Classifier: Programming Language :: Python :: 3.9
Classifier: Programming Language :: Python :: 3.10
Classifier: Programming Language :: Python :: 3.11
Classifier: Typing :: Typed
Classifier: Development Status :: 5 - Production/Stable
Classifier: License :: OSI Approved
Requires-Python: ~=3.8
License-File: LICENSE
Requires-Dist: aws-cdk-lib <3.0.0,>=2.88.0
Requires-Dist: constructs <11.0.0,>=10.0.0
Requires-Dist: jsii <2.0.0,>=1.96.0
Requires-Dist: publication >=0.0.3
Requires-Dist: typeguard ~=2.13.3
